{
  "project_info": {
    "project_number": "970038482022",
    "project_id": "calendar-junior",
    "storage_bucket": "calendar-junior.firebasestorage.app"
  },
  "client": [
    {
      "client_info": {
        "mobilesdk_app_id": "1:970038482022:android:d90bb39868072d982d89a7",
        "android_client_info": {
          "package_name": "com.example.juniorcalendar"
        }
      },
      "oauth_client": [],
      "api_key": [
        {
          "current_key": "AIzaSyBBO7LTa8I7WCu-k8x-a042kH2nPIPJcgM"
        }
      ],
      "services": {
        "appinvite_service": {
          "other_platform_oauth_client": []
        }
      }
    }
  ],
  "configuration_version": "1"
}